Metadata-Version: 2.4
Name: iflow-mcp-agoda_travel
Version: 0.2.0
Summary: Agoda offers a range of travel services, including hotel and vacation rental bookings, flights, and airport transfers. Its platform also provides exclusive deals, last-minute discounts, and a loyalty program for frequent travelers. Agoda Homes allows users to book unique stays, while Agoda VIP grants access to special rates and perks at select properties. Additionally, the platform supports travel bundles, combining flights and accommodations for cost savings.
Requires-Python: >=3.10
License-File: LICENSE
Requires-Dist: mcp>=1.6.0
Requires-Dist: pyyaml>=6.0.2
Requires-Dist: jinja2>=3.0.0
Dynamic: license-file
